odoo/addons/sale_channel_search_engine_category/README.rst
odoo/addons/sale_channel_search_engine_category/__init__.py
odoo/addons/sale_channel_search_engine_category/__manifest__.py
odoo/addons/sale_channel_search_engine_category/i18n/it.po
odoo/addons/sale_channel_search_engine_category/i18n/sale_channel_search_engine_category.pot
odoo/addons/sale_channel_search_engine_category/models/__init__.py
odoo/addons/sale_channel_search_engine_category/models/product_category.py
odoo/addons/sale_channel_search_engine_category/models/sale_channel.py
odoo/addons/sale_channel_search_engine_category/readme/CONTRIBUTORS.rst
odoo/addons/sale_channel_search_engine_category/readme/DESCRIPTION.rst
odoo/addons/sale_channel_search_engine_category/readme/HISTORY.rst
odoo/addons/sale_channel_search_engine_category/readme/newsfragments/.gitignore
odoo/addons/sale_channel_search_engine_category/static/description/icon.png
odoo/addons/sale_channel_search_engine_category/static/description/index.html
odoo/addons/sale_channel_search_engine_category/tests/__init__.py
odoo/addons/sale_channel_search_engine_category/tests/test_channel.py
odoo_addon_sale_channel_search_engine_category-16.0.0.1.2.2.dist-info/METADATA
odoo_addon_sale_channel_search_engine_category-16.0.0.1.2.2.dist-info/WHEEL
odoo_addon_sale_channel_search_engine_category-16.0.0.1.2.2.dist-info/top_level.txt
odoo_addon_sale_channel_search_engine_category-16.0.0.1.2.2.dist-info/RECORD
